LICENSE
MANIFEST.in
README.md
requirements.txt
setup.py
label_sleuth/__init__.py
label_sleuth/app.py
label_sleuth/app_utils.py
label_sleuth/authentication.py
label_sleuth/config.json
label_sleuth/config.py
label_sleuth/definitions.py
label_sleuth/start_label_sleuth.py
label_sleuth/test_app.py
label_sleuth/ui_defaults.json
label_sleuth/utils.py
label_sleuth/watsonx_config.json
label_sleuth.egg-info/PKG-INFO
label_sleuth.egg-info/SOURCES.txt
label_sleuth.egg-info/dependency_links.txt
label_sleuth.egg-info/requires.txt
label_sleuth.egg-info/top_level.txt
label_sleuth/active_learning/__init__.py
label_sleuth/active_learning/test_strategies.py
label_sleuth/active_learning/core/__init__.py
label_sleuth/active_learning/core/active_learning_api.py
label_sleuth/active_learning/core/active_learning_factory.py
label_sleuth/active_learning/core/active_learning_policies.py
label_sleuth/active_learning/core/catalog.py
label_sleuth/active_learning/policy/__init__.py
label_sleuth/active_learning/policy/active_learning_changing_policy.py
label_sleuth/active_learning/policy/active_learning_policy.py
label_sleuth/active_learning/policy/static_active_learning_policy.py
label_sleuth/active_learning/strategies/__init__.py
label_sleuth/active_learning/strategies/combined_hm_retro.py
label_sleuth/active_learning/strategies/hard_example_mining.py
label_sleuth/active_learning/strategies/hybrid_learner.py
label_sleuth/active_learning/strategies/multiclass_strategies.py
label_sleuth/active_learning/strategies/random_sampling.py
label_sleuth/active_learning/strategies/retrospective.py
label_sleuth/analysis_utils/__init__.py
label_sleuth/analysis_utils/analyze_tokens.py
label_sleuth/analysis_utils/labeling_reports.py
label_sleuth/analysis_utils/test_labeling_reports.py
label_sleuth/assets/sleuth_logo_white.svg
label_sleuth/build/asset-manifest.json
label_sleuth/build/index.html
label_sleuth/build/manifest.json
label_sleuth/build/robots.txt
label_sleuth/build/sleuth.ico
label_sleuth/build/static/css/main.35ea66e2.css
label_sleuth/build/static/css/main.35ea66e2.css.map
label_sleuth/build/static/js/main.45d2e653.js
label_sleuth/build/static/js/main.45d2e653.js.LICENSE.txt
