Metadata-Version: 2.1
Name: label-sleuth
Version: 0.20.2
Summary: Label Sleuth
Home-page: https://github.com/label-sleuth/label-sleuth
Author: IBM Research
Author-email: eyals@il.ibm.com
License: Apache License 2.0
Platform: UNKNOWN
Classifier: Programming Language :: Python :: 3
Classifier: License :: OSI Approved :: Apache Software License
Classifier: Operating System :: OS Independent
Classifier: Topic :: Scientific/Engineering
Requires-Python: >=3.9
License-File: LICENSE
